tests/__init__.py
tests/test_info.py
tests/test_merge.py
vidtoolbox/__init__.py
vidtoolbox/add_subtitles.py
vidtoolbox/generate_timestamps.py
vidtoolbox/merge_videos.py
vidtoolbox/timeline.py
vidtoolbox/video_info.py
vidtoolbox-0.1.3.dist-info/LICENSE
vidtoolbox-0.1.3.dist-info/METADATA
vidtoolbox-0.1.3.dist-info/WHEEL
vidtoolbox-0.1.3.dist-info/entry_points.txt
vidtoolbox-0.1.3.dist-info/top_level.txt
vidtoolbox-0.1.3.dist-info/RECORD
