Metadata-Version: 2.1
Name: vidtoolbox
Version: 0.1.3
Summary: A Python toolbox for managing and processing videos efficiently.
Home-page: https://github.com/nkliu1772/vidtoolbox
Author: nkliu1772
Classifier: Programming Language :: Python :: 3
Classifier: License :: OSI Approved :: MIT License
Classifier: Operating System :: OS Independent
Classifier: Topic :: Multimedia :: Video
Classifier: Intended Audience :: Developers
Classifier: Development Status :: 3 - Alpha
Requires-Python: >=3.6
License-File: LICENSE
Requires-Dist: ffmpeg-python
